{
  "tables": [
    {
      "kind": "interface",
      "name": "INav",
      "extendsTokens": [],
      "descriptionHtml": "\n",
      "members": [
        {
          "name": "selectedKey",
          "typeTokens": [
            {
              "text": "string | undefined"
            }
          ],
          "descriptionHtml": "The meta 'key' property of the currently selected NavItem of the Nav. Can return undefined if the currently selected nav item has no populated key property. Be aware that in order for Nav to properly understand which key is selected all NavItems in all groups of the Nav must have populated key properties.\n",
          "deprecated": false
        }
      ]
    },
    {
      "kind": "interface",
      "name": "INavLink",
      "extendsTokens": [],
      "descriptionHtml": "\n",
      "members": [
        {
          "name": "altText",
          "typeTokens": [
            {
              "text": "string"
            }
          ],
          "descriptionHtml": "Deprecated at v0.68.1 and will be removed at \\>= v1.0.0.\n\n",
          "deprecated": true
        },
        {
          "name": "ariaLabel",
          "typeTokens": [
            {
              "text": "string"
            }
          ],
          "descriptionHtml": "Aria label for nav link\n",
          "deprecated": false
        },
        {
          "name": "automationId",
          "typeTokens": [
            {
              "text": "string"
            }
          ],
          "descriptionHtml": "The name to use for functional automation tests\n",
          "deprecated": false
        },
        {
          "name": "disabled",
          "typeTokens": [
            {
              "text": "boolean"
            }
          ],
          "descriptionHtml": "Whether or not the link is disabled.\n",
          "deprecated": false
        },
        {
          "name": "engagementName",
          "typeTokens": [
            {
              "text": "string"
            }
          ],
          "descriptionHtml": "Deprecated at v0.68.1 and will be removed at \\>= v1.0.0.\n\n",
          "deprecated": true
        },
        {
          "name": "forceAnchor",
          "typeTokens": [
            {
              "text": "boolean"
            }
          ],
          "descriptionHtml": "(Optional) By default, any link with onClick defined will render as a button. Set this property to true to override that behavior. (Links without onClick defined will render as anchors by default.)\n",
          "deprecated": false
        },
        {
          "name": "icon",
          "typeTokens": [
            {
              "text": "string"
            }
          ],
          "descriptionHtml": "Name of an icon to render next to the link button.\n",
          "deprecated": false
        },
        {
          "name": "iconClassName",
          "typeTokens": [
            {
              "text": "string"
            }
          ],
          "descriptionHtml": "Deprecated. Use `iconProps.className` instead.\n\n",
          "deprecated": true
        },
        {
          "name": "iconProps",
          "typeTokens": [
            {
              "text": "IIconProps",
              "hyperlinkedPage": "Icon"
            }
          ],
          "descriptionHtml": "Props for an icon to render next to the link button.\n",
          "deprecated": false
        },
        {
          "name": "isExpanded",
          "typeTokens": [
            {
              "text": "boolean"
            }
          ],
          "descriptionHtml": "Whether or not the link is in an expanded state\n",
          "deprecated": false
        },
        {
          "name": "key",
          "typeTokens": [
            {
              "text": "string"
            }
          ],
          "descriptionHtml": "Unique, stable key for the link, used when rendering the list of links and for tracking the currently selected link.\n",
          "deprecated": false
        },
        {
          "name": "links",
          "typeTokens": [
            {
              "text": "INavLink",
              "hyperlinkedPage": "Nav"
            },
            {
              "text": "[]"
            }
          ],
          "descriptionHtml": "Child links to this link, if any\n",
          "deprecated": false
        },
        {
          "name": "name",
          "typeTokens": [
            {
              "text": "string"
            }
          ],
          "descriptionHtml": "Text to render for this link\n",
          "deprecated": false
        },
        {
          "name": "onClick",
          "typeTokens": [
            {
              "text": "("
            },
            {
              "text": "ev"
            },
            {
              "text": "?: "
            },
            {
              "text": "React"
            },
            {
              "text": "."
            },
            {
              "text": "MouseEvent"
            },
            {
              "text": "<"
            },
            {
              "text": "HTMLElement"
            },
            {
              "text": ">, "
            },
            {
              "text": "item"
            },
            {
              "text": "?: "
            },
            {
              "text": "INavLink",
              "hyperlinkedPage": "Nav"
            },
            {
              "text": ") => void"
            }
          ],
          "descriptionHtml": "Callback invoked when this link is clicked. Providing this callback will cause the link to render as a button (rather than an anchor) unless forceAnchor is set to true.\n",
          "deprecated": false
        },
        {
          "name": "parentId",
          "typeTokens": [
            {
              "text": "string"
            }
          ],
          "descriptionHtml": "",
          "deprecated": true
        },
        {
          "name": "target",
          "typeTokens": [
            {
              "text": "string"
            }
          ],
          "descriptionHtml": "Link <a> target.\n",
          "deprecated": false
        },
        {
          "name": "title",
          "typeTokens": [
            {
              "text": "string"
            }
          ],
          "descriptionHtml": "Text for title tooltip and ARIA description.\n",
          "deprecated": false
        },
        {
          "name": "url",
          "typeTokens": [
            {
              "text": "string"
            }
          ],
          "descriptionHtml": "URL to navigate to for this link\n",
          "deprecated": false
        }
      ]
    },
    {
      "kind": "interface",
      "name": "INavLinkGroup",
      "extendsTokens": [],
      "descriptionHtml": "\n",
      "members": [
        {
          "name": "automationId",
          "typeTokens": [
            {
              "text": "string"
            }
          ],
          "descriptionHtml": "The name to use for functional automation tests\n",
          "deprecated": false
        },
        {
          "name": "collapseByDefault",
          "typeTokens": [
            {
              "text": "boolean"
            }
          ],
          "descriptionHtml": "If true, the group should render collapsed by default\n",
          "deprecated": false
        },
        {
          "name": "links",
          "typeTokens": [
            {
              "text": "INavLink",
              "hyperlinkedPage": "Nav"
            },
            {
              "text": "[]"
            }
          ],
          "descriptionHtml": "Links to render within this group\n",
          "deprecated": false
        },
        {
          "name": "name",
          "typeTokens": [
            {
              "text": "string"
            }
          ],
          "descriptionHtml": "Text to render as the header of a group\n",
          "deprecated": false
        },
        {
          "name": "onHeaderClick",
          "typeTokens": [
            {
              "text": "("
            },
            {
              "text": "ev"
            },
            {
              "text": "?: "
            },
            {
              "text": "React"
            },
            {
              "text": "."
            },
            {
              "text": "MouseEvent"
            },
            {
              "text": "<"
            },
            {
              "text": "HTMLElement"
            },
            {
              "text": ">, "
            },
            {
              "text": "isCollapsing"
            },
            {
              "text": "?: boolean) => void"
            }
          ],
          "descriptionHtml": "Callback invoked when a group header is clicked\n",
          "deprecated": false
        }
      ]
    },
    {
      "kind": "interface",
      "name": "INavProps",
      "extendsTokens": [],
      "descriptionHtml": "\n",
      "members": [
        {
          "name": "ariaLabel",
          "typeTokens": [
            {
              "text": "string"
            }
          ],
          "descriptionHtml": "(Optional) The nav container aria label.\n",
          "deprecated": false
        },
        {
          "name": "className",
          "typeTokens": [
            {
              "text": "string"
            }
          ],
          "descriptionHtml": "Additional css class to apply to the Nav\n\n",
          "deprecated": false
        },
        {
          "name": "collapsedStateText",
          "typeTokens": [
            {
              "text": "string"
            }
          ],
          "descriptionHtml": "Deprecated at v0.68.1 and will be removed at \\>= v1.0.0.\n\n",
          "deprecated": true
        },
        {
          "name": "componentRef",
          "typeTokens": [
            {
              "text": "IRefObject"
            },
            {
              "text": "<"
            },
            {
              "text": "INav",
              "hyperlinkedPage": "Nav"
            },
            {
              "text": ">"
            }
          ],
          "descriptionHtml": "Optional callback to access the INav interface. Use this instead of ref for accessing the public methods and properties of the component.\n",
          "deprecated": false
        },
        {
          "name": "expandButtonAriaLabel",
          "typeTokens": [
            {
              "text": "string"
            }
          ],
          "descriptionHtml": "(Optional) The nav container aria label.\n",
          "deprecated": false
        },
        {
          "name": "expandedStateText",
          "typeTokens": [
            {
              "text": "string"
            }
          ],
          "descriptionHtml": "Deprecated at v0.68.1 and will be removed at \\>= v1.0.0.\n\n",
          "deprecated": true
        },
        {
          "name": "groups",
          "typeTokens": [
            {
              "text": "INavLinkGroup",
              "hyperlinkedPage": "Nav"
            },
            {
              "text": "[] | null"
            }
          ],
          "descriptionHtml": "A collection of link groups to display in the navigation bar\n",
          "deprecated": false
        },
        {
          "name": "initialSelectedKey",
          "typeTokens": [
            {
              "text": "string"
            }
          ],
          "descriptionHtml": "(Optional) The key of the nav item initially selected.\n",
          "deprecated": false
        },
        {
          "name": "isOnTop",
          "typeTokens": [
            {
              "text": "boolean"
            }
          ],
          "descriptionHtml": "Indicates whether the navigation component renders on top of other content in the UI\n",
          "deprecated": false
        },
        {
          "name": "linkAs",
          "typeTokens": [
            {
              "text": "IComponentAs"
            },
            {
              "text": "<"
            },
            {
              "text": "IButtonProps",
              "hyperlinkedPage": "Button"
            },
            {
              "text": ">"
            }
          ],
          "descriptionHtml": "Render a custom link in place of the normal one. This replaces the entire button rather than simply button content\n",
          "deprecated": false
        },
        {
          "name": "onLinkClick",
          "typeTokens": [
            {
              "text": "("
            },
            {
              "text": "ev"
            },
            {
              "text": "?: "
            },
            {
              "text": "React"
            },
            {
              "text": "."
            },
            {
              "text": "MouseEvent"
            },
            {
              "text": "<"
            },
            {
              "text": "HTMLElement"
            },
            {
              "text": ">, "
            },
            {
              "text": "item"
            },
            {
              "text": "?: "
            },
            {
              "text": "INavLink",
              "hyperlinkedPage": "Nav"
            },
            {
              "text": ") => void"
            }
          ],
          "descriptionHtml": "Function callback invoked when a link in the navigation is clicked\n",
          "deprecated": false
        },
        {
          "name": "onLinkExpandClick",
          "typeTokens": [
            {
              "text": "("
            },
            {
              "text": "ev"
            },
            {
              "text": "?: "
            },
            {
              "text": "React"
            },
            {
              "text": "."
            },
            {
              "text": "MouseEvent"
            },
            {
              "text": "<"
            },
            {
              "text": "HTMLElement"
            },
            {
              "text": ">, "
            },
            {
              "text": "item"
            },
            {
              "text": "?: "
            },
            {
              "text": "INavLink",
              "hyperlinkedPage": "Nav"
            },
            {
              "text": ") => void"
            }
          ],
          "descriptionHtml": "Function callback invoked when the chevron on a link is clicked\n",
          "deprecated": false
        },
        {
          "name": "onRenderGroupHeader",
          "typeTokens": [
            {
              "text": "IRenderFunction"
            },
            {
              "text": "<"
            },
            {
              "text": "INavLinkGroup",
              "hyperlinkedPage": "Nav"
            },
            {
              "text": ">"
            }
          ],
          "descriptionHtml": "Used to customize how content inside the group header is rendered\n\n",
          "deprecated": false
        },
        {
          "name": "onRenderLink",
          "typeTokens": [
            {
              "text": "IRenderFunction"
            },
            {
              "text": "<"
            },
            {
              "text": "INavLink",
              "hyperlinkedPage": "Nav"
            },
            {
              "text": ">"
            }
          ],
          "descriptionHtml": "Used to customize how content inside the link tag is rendered\n\n",
          "deprecated": false
        },
        {
          "name": "selectedKey",
          "typeTokens": [
            {
              "text": "string"
            }
          ],
          "descriptionHtml": "(Optional) The key of the nav item selected by caller.\n",
          "deprecated": false
        },
        {
          "name": "styles",
          "typeTokens": [
            {
              "text": "IStyleFunctionOrObject"
            },
            {
              "text": "<"
            },
            {
              "text": "INavStyleProps",
              "hyperlinkedPage": "Nav"
            },
            {
              "text": ", "
            },
            {
              "text": "INavStyles",
              "hyperlinkedPage": "Nav"
            },
            {
              "text": ">"
            }
          ],
          "descriptionHtml": "Call to provide customized styling that will layer on top of the variant rules\n",
          "deprecated": false
        },
        {
          "name": "theme",
          "typeTokens": [
            {
              "text": "ITheme"
            }
          ],
          "descriptionHtml": "Theme provided by HOC.\n",
          "deprecated": false
        }
      ]
    },
    {
      "kind": "interface",
      "name": "INavStyleProps",
      "extendsTokens": [],
      "descriptionHtml": "\n",
      "members": [
        {
          "name": "className",
          "typeTokens": [
            {
              "text": "string"
            }
          ],
          "descriptionHtml": "Accept custom classNames\n",
          "deprecated": false
        },
        {
          "name": "groups",
          "typeTokens": [
            {
              "text": "INavLinkGroup",
              "hyperlinkedPage": "Nav"
            },
            {
              "text": "[] | null"
            }
          ],
          "descriptionHtml": "Inherited from INavProps A collection of link groups to display in the navigation bar\n",
          "deprecated": false
        },
        {
          "name": "isButtonEntry",
          "typeTokens": [
            {
              "text": "boolean"
            }
          ],
          "descriptionHtml": "is button\n",
          "deprecated": false
        },
        {
          "name": "isDisabled",
          "typeTokens": [
            {
              "text": "boolean"
            }
          ],
          "descriptionHtml": "is element disabled\n",
          "deprecated": false
        },
        {
          "name": "isExpanded",
          "typeTokens": [
            {
              "text": "boolean"
            }
          ],
          "descriptionHtml": "is element expanded boolean\n",
          "deprecated": false
        },
        {
          "name": "isGroup",
          "typeTokens": [
            {
              "text": "boolean"
            }
          ],
          "descriptionHtml": "is element a group boolean\n",
          "deprecated": false
        },
        {
          "name": "isLink",
          "typeTokens": [
            {
              "text": "boolean"
            }
          ],
          "descriptionHtml": "is element a link boolean\n",
          "deprecated": false
        },
        {
          "name": "isOnTop",
          "typeTokens": [
            {
              "text": "boolean"
            }
          ],
          "descriptionHtml": "is element on top boolean\n",
          "deprecated": false
        },
        {
          "name": "isSelected",
          "typeTokens": [
            {
              "text": "boolean"
            }
          ],
          "descriptionHtml": "is element selected boolean\n",
          "deprecated": false
        },
        {
          "name": "leftPadding",
          "typeTokens": [
            {
              "text": "number"
            }
          ],
          "descriptionHtml": "left padding value\n",
          "deprecated": false
        },
        {
          "name": "leftPaddingExpanded",
          "typeTokens": [
            {
              "text": "number"
            }
          ],
          "descriptionHtml": "left padding when expanded value\n",
          "deprecated": false
        },
        {
          "name": "navHeight",
          "typeTokens": [
            {
              "text": "number"
            }
          ],
          "descriptionHtml": "Nav height value\n",
          "deprecated": false
        },
        {
          "name": "position",
          "typeTokens": [
            {
              "text": "number"
            }
          ],
          "descriptionHtml": "position value\n",
          "deprecated": false
        },
        {
          "name": "rightPadding",
          "typeTokens": [
            {
              "text": "number"
            }
          ],
          "descriptionHtml": "right padding value\n",
          "deprecated": false
        },
        {
          "name": "theme",
          "typeTokens": [
            {
              "text": "ITheme"
            }
          ],
          "descriptionHtml": "Accept theme prop.\n",
          "deprecated": false
        }
      ]
    },
    {
      "kind": "interface",
      "name": "INavStyles",
      "extendsTokens": [],
      "descriptionHtml": "\n",
      "members": [
        {
          "name": "chevronButton",
          "typeTokens": [
            {
              "text": "IStyle"
            }
          ],
          "descriptionHtml": "Style set for the chevron button inside the composite link and group elements.\n",
          "deprecated": false
        },
        {
          "name": "chevronIcon",
          "typeTokens": [
            {
              "text": "IStyle"
            }
          ],
          "descriptionHtml": "Style set for the chevron icon inside the composite link and group elements.\n",
          "deprecated": false
        },
        {
          "name": "compositeLink",
          "typeTokens": [
            {
              "text": "IStyle"
            }
          ],
          "descriptionHtml": "Style set for the composite link container div element\n",
          "deprecated": false
        },
        {
          "name": "group",
          "typeTokens": [
            {
              "text": "IStyle"
            }
          ],
          "descriptionHtml": "Style set for the group root div.\n",
          "deprecated": false
        },
        {
          "name": "groupContent",
          "typeTokens": [
            {
              "text": "IStyle"
            }
          ],
          "descriptionHtml": "Style set for the group content div inside group.\n",
          "deprecated": false
        },
        {
          "name": "link",
          "typeTokens": [
            {
              "text": "IStyle"
            }
          ],
          "descriptionHtml": "Style set for the link element extending the root style set for ActionButton component.\n",
          "deprecated": false
        },
        {
          "name": "linkText",
          "typeTokens": [
            {
              "text": "IStyle"
            }
          ],
          "descriptionHtml": "Style set for the link text container div element.\n",
          "deprecated": false
        },
        {
          "name": "navItem",
          "typeTokens": [
            {
              "text": "IStyle"
            }
          ],
          "descriptionHtml": "Style set for the nav links li element.\n",
          "deprecated": false
        },
        {
          "name": "navItems",
          "typeTokens": [
            {
              "text": "IStyle"
            }
          ],
          "descriptionHtml": "Style set for the nav links ul element.\n",
          "deprecated": false
        },
        {
          "name": "root",
          "typeTokens": [
            {
              "text": "IStyle"
            }
          ],
          "descriptionHtml": "Style set for the root element.\n",
          "deprecated": false
        }
      ]
    }
  ]
}
